<?xml version="1.0" encoding="utf-8" ?><dwsync><file name="breadcrumb_navxt_admin.php" server="50.87.248.72//" local="3498748119" remote="319783739142587788" Dst="-1" /><file name="breadcrumb-navxt.php" server="50.87.248.72//" local="3498748119" remote="319783739142587788" Dst="-1" /><file name="class.bcn_breadcrumb.php" server="50.87.248.72//" local="3498748120" remote="319783739142587788" Dst="-1" /><file name="class.bcn_admin.php" server="50.87.248.72//" local="3498748120" remote="319783739142587788" Dst="-1" /><file name="class.bcn_uninstaller.php" server="50.87.248.72//" local="3498748120" remote="319783739142587788" Dst="-1" /><file name="class.bcn_breadcrumb_trail.php" server="50.87.248.72//" local="3498748120" remote="319783739142587788" Dst="-1" /><file name="class.bcn_network_admin.php" server="50.87.248.72//" local="3498748120" remote="319783739142587788" Dst="-1" /><file name="class.bcn_widget.php" server="50.87.248.72//" local="3498748121" remote="319783739142587788" Dst="-1" /><file name="uninstall.php" server="50.87.248.72//" local="3498748128" remote="319783739142587788" Dst="-1" /><file name="readme.txt" server="50.87.248.72//" local="3498748128" remote="319783739142587788" Dst="-1" /></dwsync>